wagtailset/draftail_anchors/__init__.py
wagtailset/draftail_anchors/apps.py
wagtailset/draftail_anchors/rich_text.py
wagtailset/draftail_anchors/wagtail_hooks.py
wagtailset/draftail_anchors/static/wagtailsetdraftailanchors/js/wagtailset-draftail-anchor.js
wagtailset/draftail_anchors/templates/wagtailsetdraftailanchors/icons/anchor.svg
wagtailset-1.1.4.dist-info/METADATA
wagtailset-1.1.4.dist-info/WHEEL
wagtailset-1.1.4.dist-info/top_level.txt
wagtailset-1.1.4.dist-info/RECORD
