Metadata-Version: 2.4
Name: wagtailset
Version: 1.1.4
Summary: Wagtail anchors set
Author-email: Ihor Marhytich <dest81@gmail.com>
License: MIT License
Project-URL: Homepage, https://github.com/dest81/wagtailset
Project-URL: Bug Tracker, https://github.com/dest81/wagtailset/issues
Keywords: wagtail,draftail,anchors
Classifier: Programming Language :: Python :: 3
Classifier: License :: OSI Approved :: MIT License
Classifier: Operating System :: OS Independent
Requires-Python: >=3.7
Requires-Dist: wagtail>2.9
